apideck_unify/__init__.py
apideck_unify/_hooks/__init__.py
apideck_unify/_hooks/registration.py
apideck_unify/_hooks/sdkhooks.py
apideck_unify/_hooks/types.py
apideck_unify/_version.py
apideck_unify/accounting.py
apideck_unify/activities.py
apideck_unify/agedcreditors_sdk.py
apideck_unify/ageddebtors_sdk.py
apideck_unify/apideck_companies.py
apideck_unify/apideck_customers.py
apideck_unify/apideck_departments.py
apideck_unify/apiresourcecoverage_sdk.py
apideck_unify/apiresources.py
apideck_unify/apis.py
apideck_unify/applicants.py
apideck_unify/applications.py
apideck_unify/ats.py
apideck_unify/attachments.py
apideck_unify/balancesheet_sdk.py
apideck_unify/bankaccounts.py
apideck_unify/bankfeedaccounts.py
apideck_unify/bankfeedstatements.py
apideck_unify/basesdk.py
apideck_unify/billpayments.py
apideck_unify/bills.py
apideck_unify/categories.py
apideck_unify/collections.py
apideck_unify/collectiontags.py
apideck_unify/collectionticketcomments.py
apideck_unify/collectiontickets.py
apideck_unify/collectionusers.py
apideck_unify/companies.py
apideck_unify/companyinfo_sdk.py
apideck_unify/connectionconsent.py
apideck_unify/connectionconsents.py
apideck_unify/connectioncustommappings.py
apideck_unify/connections.py
apideck_unify/connectionsettings.py
apideck_unify/connector_sdk.py
apideck_unify/connectordocs.py
apideck_unify/connectorresources.py
apideck_unify/connectors.py
apideck_unify/consumerrequestcounts.py
apideck_unify/consumers.py
apideck_unify/contacts.py
apideck_unify/createcallback.py
apideck_unify/creditnotes.py
apideck_unify/crm.py
apideck_unify/customers.py
apideck_unify/customfields.py
apideck_unify/custommappings.py
apideck_unify/customobjects.py
apideck_unify/customobjectschemas.py
apideck_unify/departments.py
apideck_unify/drivegroups.py
apideck_unify/drives.py
apideck_unify/ecommerce.py
apideck_unify/employeepayrolls.py
apideck_unify/employees.py
apideck_unify/employeeschedules_sdk.py
apideck_unify/eventlogs.py
apideck_unify/expenses.py
apideck_unify-0.30.0.dist-info/METADATA
apideck_unify-0.30.0.dist-info/WHEEL
apideck_unify-0.30.0.dist-info/RECORD
